thriftcli/__init__.py
thriftcli/__main__.py
thriftcli/java_thrift_request_body_converter.py
thriftcli/json_request_body_converter.py
thriftcli/request_body_converter.py
thriftcli/thrift_argument_converter.py
thriftcli/thrift_cli.py
thriftcli/thrift_cli_error.py
thriftcli/thrift_executor.py
thriftcli/thrift_parse_result.py
thriftcli/thrift_parser.py
thriftcli/thrift_service.py
thriftcli/thrift_struct.py
thriftcli/thrift_zookeeper_resolver.py
thriftcli2-1.1.dist-info/METADATA
thriftcli2-1.1.dist-info/RECORD
thriftcli2-1.1.dist-info/WHEEL
thriftcli2-1.1.dist-info/entry_points.txt
thriftcli2-1.1.dist-info/top_level.txt
